LICENSE
ply2splat/__init__.py
ply2splat/ply2splat.cpython-39-darwin.so
ply2splat-0.6.0.dist-info/METADATA
ply2splat-0.6.0.dist-info/WHEEL
ply2splat-0.6.0.dist-info/entry_points.txt
ply2splat-0.6.0.dist-info/licenses/LICENSE
ply2splat-0.6.0.dist-info/RECORD
