Metadata-Version: 2.4
Name: ply2splat
Version: 0.6.0
Classifier: Development Status :: 4 - Beta
Classifier: Intended Audience :: Developers
Classifier: Intended Audience :: Science/Research
Classifier: License :: OSI Approved :: MIT License
Classifier: Operating System :: OS Independent
Classifier: Programming Language :: Python :: 3
Classifier: Programming Language :: Python :: 3.9
Classifier: Programming Language :: Python :: 3.10
Classifier: Programming Language :: Python :: 3.11
Classifier: Programming Language :: Python :: 3.12
Classifier: Programming Language :: Python :: 3.13
Classifier: Programming Language :: Rust
Classifier: Topic :: Multimedia :: Graphics :: 3D Rendering
License-File: LICENSE
Summary: A high-performance library for converting Gaussian Splatting PLY files to SPLAT format
Keywords: graphics,gaussian-splatting,ply,splat,3d,rendering
Requires-Python: >=3.9
Project-URL: Homepage, https://github.com/bastikohn/ply2splat
Project-URL: Repository, https://github.com/bastikohn/ply2splat
